text_lloom/__init__.py
text_lloom/concept.py
text_lloom/concept_induction.py
text_lloom/llm.py
text_lloom/llm_openai.py
text_lloom/prompts.py
text_lloom/static/index.css
text_lloom/static/index.js
text_lloom/static/index_select.css
text_lloom/static/index_select.js
text_lloom/workbench.py
text_lloom-0.8.2.dist-info/METADATA
text_lloom-0.8.2.dist-info/WHEEL
text_lloom-0.8.2.dist-info/RECORD
